nbeats_keras/__init__.py
nbeats_keras/model.py
nbeats_keras-1.8.0.dist-info/LICENSE
nbeats_keras-1.8.0.dist-info/METADATA
nbeats_keras-1.8.0.dist-info/WHEEL
nbeats_keras-1.8.0.dist-info/top_level.txt
nbeats_keras-1.8.0.dist-info/RECORD
