Metadata-Version: 2.1
Name: nbeats-keras
Version: 1.8.0
Summary: N-Beats
Author: Philippe Remy (Pytorch), Jean Sebastien Dhr (Keras)
License: MIT
License-File: LICENSE
Requires-Dist: numpy
Requires-Dist: keract
Requires-Dist: pandas
Requires-Dist: matplotlib
Requires-Dist: protobuf (<=3.20)
Requires-Dist: keras
Requires-Dist: tensorflow
